wjkutil/__init__.py
wjkutil/inputs.py
wjkutil/util.py
wjkutil/xor/__init__.py
wjkutil/xor/__main__.py
wjkutil/xor/guess_len.py
wjkutil/xor/single_char_xor.py
wjkutil/xor/util.py
wjkutil-0.0.1.dist-info/METADATA
wjkutil-0.0.1.dist-info/WHEEL
wjkutil-0.0.1.dist-info/top_level.txt
wjkutil-0.0.1.dist-info/RECORD
