Metadata-Version: 2.1
Name: wjkutil
Version: 0.0.1
Summary: A util package containing many useful wrappers
Author-email: am009 <warrenwjk@gmail.com>
Classifier: Programming Language :: Python :: 3
Classifier: License :: OSI Approved :: MIT License
Classifier: Operating System :: OS Independent
Requires-Python: >=3.1
